magic_constraints/__init__.py
magic_constraints/argument.py
magic_constraints/constraint.py
magic_constraints/decorator.py
magic_constraints/exception.py
magic_constraints/metadata.py
magic_constraints/types.py
magic_constraints/utils.py
magic_constraints-0.4.0.dist-info/DESCRIPTION.rst
magic_constraints-0.4.0.dist-info/METADATA
magic_constraints-0.4.0.dist-info/RECORD
magic_constraints-0.4.0.dist-info/WHEEL
magic_constraints-0.4.0.dist-info/entry_points.txt
magic_constraints-0.4.0.dist-info/metadata.json
magic_constraints-0.4.0.dist-info/top_level.txt
